lenjou_prompt/__init__.py
lenjou_prompt/prompt.py
lenjou_prompt-0.0.1.dist-info/LICENSE
lenjou_prompt-0.0.1.dist-info/METADATA
lenjou_prompt-0.0.1.dist-info/WHEEL
lenjou_prompt-0.0.1.dist-info/top_level.txt
lenjou_prompt-0.0.1.dist-info/RECORD
